[
    {
        "firstname": "Abdurrahim",
        "lastname": "Suslu",
        "position": "Regional Sales Manager - Dubai",
        "n+1": "ahmed.hamza@intersec.com",
        "img": "intersecAmazingPeople/Abdurrahim Suslu/Abdurrahim_SUSLU.jpg",
        "tags": "",
        "email": "abdurrahim.suslu@intersec.com",
        "id": "abdurrahim.suslu@intersec.com",
        "parentId": "ahmed.hamza@intersec.com"
    },
    {
        "firstname": "Adel",
        "lastname": "Amri",
        "position": "Solution Architect",
        "n+1": "nicolas.najman@intersec.com",
        "img": "intersecAmazingPeople/Adel Amri/Adel.Amri.jpg",
        "tags": "",
        "email": "adel.amri@intersec.com",
        "id": "adel.amri@intersec.com",
        "parentId": "nicolas.najman@intersec.com"
    },
    {
        "firstname": "Ahmed",
        "lastname": "Hamza",
        "position": "VP Sales",
        "n+1": "ingolf.ruh@intersec.com",
        "img": "intersecAmazingPeople/Ahmed Hamza/HAMZA.Ahmed.jpg",
        "tags": "management",
        "email": "ahmed.hamza@intersec.com",
        "id": "ahmed.hamza@intersec.com",
        "parentId": "ingolf.ruh@intersec.com"
    },
    {
        "firstname": "Ahmed",
        "lastname": "Majdouba",
        "position": "Support Engineer",
        "n+1": "onur.topcu@intersec.com",
        "img": "intersecAmazingPeople/Ahmed Ben Majdouba/Ahmed_BENMAJDOUBA.jpg",
        "tags": "",
        "email": "ahmed.majdouba@intersec.com",
        "id": "ahmed.majdouba@intersec.com",
        "parentId": "onur.topcu@intersec.com"
    },
    {
        "firstname": "Alexandre",
        "lastname": "Prengere",
        "position": "Project Manager",
        "n+1": "emilien.coffin@intersec.com",
        "img": "intersecAmazingPeople/Alexandre Prengere/Alexandre.Prengere.jpg",
        "tags": "",
        "email": "alexandre.prengere@intersec.com",
        "id": "alexandre.prengere@intersec.com",
        "parentId": "emilien.coffin@intersec.com"
    },
    {
        "firstname": "Ahmed",
        "lastname": "Lyahou",
        "position": "Presales",
        "n+1": "ingolf.ruh@intersec.com",
        "img": "intersecAmazingPeople/Ahmed Lyahou/Ahmed_LYAHOU.jpg",
        "tags": "",
        "email": "ahmed.lyahou@intersec.com",
        "id": "ahmed.lyahou@intersec.com",
        "parentId": "ingolf.ruh@intersec.com"
    },
    {
        "firstname": "Alexandre",
        "lastname": "Quince",
        "position": "Sales Development Representative",
        "n+1": "ingolf.ruh@intersec.com",
        "img": "intersecAmazingPeople/Alexandre Quince/alex.jpg",
        "tags": "",
        "email": "alexandre.quince@intersec.com",
        "id": "alexandre.quince@intersec.com",
        "parentId": "ingolf.ruh@intersec.com"
    },
    {
        "firstname": "Alexandre",
        "lastname": "Riquier",
        "position": "Integration Engineer",
        "n+1": "simon.ravier@intersec.com",
        "img": "intersecAmazingPeople/Alexandre Riquier/Alexandre_Riquier.jpg",
        "tags": "",
        "email": "alexandre.riquier@intersec.com",
        "id": "alexandre.riquier@intersec.com",
        "parentId": "simon.ravier@intersec.com"
    },
    {
        "firstname": "Alexis",
        "lastname": "Brasy",
        "position": "Team Leader",
        "n+1": "mohamed.kahlal@intersec.com",
        "img": "intersecAmazingPeople/Alexis Brasy/Brasy.Alexis.jpg",
        "tags": "",
        "email": "alexis.brasy@intersec.com",
        "id": "alexis.brasy@intersec.com",
        "parentId": "mohamed.kahlal@intersec.com"
    },
    {
        "firstname": "Alex",
        "lastname": "Slavutskyi",
        "position": "UX/UI Designer",
        "n+1": "kamal.fadlaoui@intersec.com",
        "img": "intersecAmazingPeople/Alex Slavutskyi/Alex.Slavutskyi.jpg",
        "tags": "",
        "email": "alex.slavutskyi@intersec.com",
        "id": "alex.slavutskyi@intersec.com",
        "parentId": "kamal.fadlaoui@intersec.com"
    },
    {
        "firstname": "Anand",
        "lastname": "Panwar",
        "position": "Integration Engineer",
        "n+1": "haytham.beshir@intersec.com",
        "img": "intersecAmazingPeople/Anand Panwar/Anand.Panwar.jpg",
        "tags": "",
        "email": "anand.panwar@intersec.com",
        "id": "anand.panwar@intersec.com",
        "parentId": "haytham.beshir@intersec.com"
    },
    {
        "firstname": "Amira",
        "lastname": "Bouali",
        "position": "Developer",
        "n+1": "rawad.zgheib@intersec.com",
        "img": "intersecAmazingPeople/Amira Hadjer Bouali/Bouali.Amira.jpg",
        "tags": "",
        "email": "amira.bouali@intersec.com",
        "id": "amira.bouali@intersec.com",
        "parentId": "rawad.zgheib@intersec.com"
    },
    {
        "firstname": "Anas",
        "lastname": "Mohamed",
        "position": "Integration Engineer (Egypt)",
        "n+1": "neeraj.bhatnagar@intersec.com",
        "img": "intersecAmazingPeople/Anas Mohamed/Anas_Mohamed.jpg",
        "tags": "",
        "email": "anas.mohamed@intersec.com",
        "id": "anas.mohamed@intersec.com",
        "parentId": "neeraj.bhatnagar@intersec.com"
    },
    {
        "firstname": "Aneep",
        "lastname": "Srivastava",
        "position": "Solution Architect",
        "n+1": "nicolas.najman@intersec.com",
        "img": "intersecAmazingPeople/Aneep Srivastava/Srivastava.Aneep.png",
        "tags": "",
        "email": "aneep.srivastava@intersec.com",
        "id": "aneep.srivastava@intersec.com",
        "parentId": "nicolas.najman@intersec.com"
    },
    {
        "firstname": "Antoine",
        "lastname": "Debroye",
        "position": "Continuous Integrator",
        "n+1": "alexis.brasy@intersec.com",
        "img": "intersecAmazingPeople/Antoine Debroye/DEBROYE.Antoine.jpg",
        "tags": "",
        "email": "antoine.debroye@intersec.com",
        "id": "antoine.debroye@intersec.com",
        "parentId": "alexis.brasy@intersec.com"
    },
    {
        "firstname": "Ali",
        "lastname": "Houssni",
        "position": "Presales",
        "n+1": "ingolf.ruh@intersec.com",
        "img": "intersecAmazingPeople/Ali Houssni/Houssni.Ali.jpg",
        "tags": "",
        "email": "ali.houssni@intersec.com",
        "id": "ali.houssni@intersec.com",
        "parentId": "ingolf.ruh@intersec.com"
    },
    {
        "firstname": "Anne-Laurence",
        "lastname": "Zanclan",
        "position": "Hiring Consultant",
        "n+1": "oyo.ndoro@intersec.com",
        "img": "intersecAmazingPeople/Anne-Laurence Zanclan/ZANCLAN.Anne-Laurence.jpg",
        "tags": "",
        "email": "anne-laurence.zanclan@intersec.com",
        "id": "anne-laurence.zanclan@intersec.com",
        "parentId": "oyo.ndoro@intersec.com"
    },
    {
        "firstname": "Aline",
        "lastname": "Fauquette",
        "position": "DevOps Engineer",
        "n+1": "jean-marc.coic@intersec.com",
        "img": "intersecAmazingPeople/Aline Fauquette/Fauquette.Aline.jpg",
        "tags": "",
        "email": "aline.fauquette@intersec.com",
        "id": "aline.fauquette@intersec.com",
        "parentId": "jean-marc.coic@intersec.com"
    },
    {
        "firstname": "Arnaud",
        "lastname": "Westphal",
        "position": "VP Sales",
        "n+1": "ingolf.ruh@intersec.com",
        "img": "intersecAmazingPeople/Arnaud Westphal/WESTPHAL.Arnaud.JPG",
        "tags": "management",
        "email": "arnaud.westphal@intersec.com",
        "id": "arnaud.westphal@intersec.com",
        "parentId": "ingolf.ruh@intersec.com"
    },
    {
        "firstname": "Benoit",
        "lastname": "Mariat",
        "position": "Software Architect",
        "n+1": "jean-marc.coic@intersec.com",
        "img": "intersecAmazingPeople/Benoit Mariat/Mariat.benoit.jpg",
        "tags": "",
        "email": "benoit.mariat@intersec.com",
        "id": "benoit.mariat@intersec.com",
        "parentId": "jean-marc.coic@intersec.com"
    },
    {
        "firstname": "Caroline",
        "lastname": "Dumaitre",
        "position": "Accounting and Financial Manager",
        "n+1": "nicolas.dumarcet@intersec.com",
        "img": "intersecAmazingPeople/Caroline Dumaitre/Dumaitre.Caroline.png",
        "tags": "",
        "email": "caroline.dumaitre@intersec.com",
        "id": "caroline.dumaitre@intersec.com",
        "parentId": "nicolas.dumarcet@intersec.com"
    },
    {
        "firstname": "Braulio",
        "lastname": "Castillo",
        "position": "Solution Architect",
        "n+1": "nicolas.najman@intersec.com",
        "img": "intersecAmazingPeople/Braulio Castillo/Castillo.Braulio.jpg",
        "tags": "",
        "email": "braulio.castillo@intersec.com",
        "id": "braulio.castillo@intersec.com",
        "parentId": "nicolas.najman@intersec.com"
    },
    {
        "firstname": "Charlotte",
        "lastname": "Cardona",
        "position": "Marketing & Communication Director",
        "n+1": "yann.chevalier@intersec.com",
        "img": "intersecAmazingPeople/Charlotte Cardona/Cardona.Charlotte.png",
        "tags": "management",
        "email": "charlotte.cardona@intersec.com",
        "id": "charlotte.cardona@intersec.com",
        "parentId": "yann.chevalier@intersec.com"
    },
    {
        "firstname": "Chiheb",
        "lastname": "Bestaoui",
        "position": "Integration Engineer",
        "n+1": "emilien.coffin@intersec.com",
        "img": "intersecAmazingPeople/Chiheb Bestaoui/chiheb_bestaoui.jpg",
        "tags": "",
        "email": "chiheb.bestaoui@intersec.com",
        "id": "chiheb.bestaoui@intersec.com",
        "parentId": "emilien.coffin@intersec.com"
    },
    {
        "firstname": "Cedrick",
        "lastname": "Vero",
        "position": "Presales",
        "n+1": "ingolf.ruh@intersec.com",
        "img": "intersecAmazingPeople/Cedrick Vero/Vero.Cedrick.png",
        "tags": "",
        "email": "cedrick.vero@intersec.com",
        "id": "cedrick.vero@intersec.com",
        "parentId": "ingolf.ruh@intersec.com"
    },
    {
        "firstname": "Charlotte",
        "lastname": "Thomas",
        "position": "Cloud Offering Director",
        "n+1": "christophe.nez@intersec.com",
        "img": "intersecAmazingPeople/Charlotte Thomas/Charlotte_THOMAS.jpg",
        "tags": "",
        "email": "charlotte.thomas@intersec.com",
        "id": "charlotte.thomas@intersec.com",
        "parentId": "christophe.nez@intersec.com"
    },
    {
        "firstname": "Chloe",
        "lastname": "Maroun",
        "position": "Presales",
        "n+1": "ingolf.ruh@intersec.com",
        "img": "intersecAmazingPeople/Chloe Maroun/chloe.jpg",
        "tags": "",
        "email": "chloe.maroun@intersec.com",
        "id": "chloe.maroun@intersec.com",
        "parentId": "ingolf.ruh@intersec.com"
    },
    {
        "firstname": "Christele",
        "lastname": "Camara",
        "position": "Technical Documentation Manager",
        "n+1": "kamal.fadlaoui@intersec.com",
        "img": "intersecAmazingPeople/Christele Camara/christele.jpg",
        "tags": "",
        "email": "christele.camara@intersec.com",
        "id": "christele.camara@intersec.com",
        "parentId": "kamal.fadlaoui@intersec.com"
    },
    {
        "firstname": "Christophe",
        "lastname": "Gosset",
        "position": "Data Scientist",
        "n+1": "pierre-louis.cuny@intersec.com",
        "img": "intersecAmazingPeople/Christophe Gosset/Gosset.Christophe.jpg",
        "tags": "",
        "email": "christophe.gosset@intersec.com",
        "id": "christophe.gosset@intersec.com",
        "parentId": "pierre-louis.cuny@intersec.com"
    },
    {
        "firstname": "Christophe",
        "lastname": "Nez",
        "position": "VP Product Marketing",
        "n+1": "yann.chevalier@intersec.com",
        "img": "intersecAmazingPeople/Christophe Nez/NEZ.christophe.png",
        "tags": "management",
        "email": "christophe.nez@intersec.com",
        "id": "christophe.nez@intersec.com",
        "parentId": "yann.chevalier@intersec.com"
    },
    {
        "firstname": "Clement",
        "lastname": "Vandoolaeghe",
        "position": "Head of Platform Operations",
        "n+1": "jean-marc.coic@intersec.com",
        "img": "intersecAmazingPeople/Clement Vandoolaeghe/Clem.jpg",
        "tags": "",
        "email": "clement.vandoolaeghe@intersec.com",
        "id": "clement.vandoolaeghe@intersec.com",
        "parentId": "jean-marc.coic@intersec.com"
    },
    {
        "firstname": "Curtis",
        "lastname": "Jameson",
        "position": "Integration Engineer",
        "n+1": "matthias.granger@intersec.com",
        "img": "intersecAmazingPeople/Curtis Jameson/Jameson.Curtis.png",
        "tags": "",
        "email": "curtis.jameson@intersec.com",
        "id": "curtis.jameson@intersec.com",
        "parentId": "matthias.granger@intersec.com"
    },
    {
        "firstname": "Dihia",
        "lastname": "Salhi",
        "position": "Continuous Integrator",
        "n+1": "rawad.zgheib@intersec.com",
        "img": "intersecAmazingPeople/Dihia Salhi/Dihia_SALHI.jpg",
        "tags": "",
        "email": "dihia.salhi@intersec.com",
        "id": "dihia.salhi@intersec.com",
        "parentId": "rawad.zgheib@intersec.com"
    },
    {
        "firstname": "David",
        "lastname": "Fontmartin",
        "position": "Solution Architect",
        "n+1": "nicolas.najman@intersec.com",
        "img": "intersecAmazingPeople/David Fontmartin/FONTMARTIN.David.jpg",
        "tags": "",
        "email": "david.fontmartin@intersec.com",
        "id": "david.fontmartin@intersec.com",
        "parentId": "nicolas.najman@intersec.com"
    },
    {
        "firstname": "Daosavanh",
        "lastname": "Thepsouvanh",
        "position": "Continuous Integrator",
        "n+1": "nassim.mnafeg@intersec.com",
        "img": "intersecAmazingPeople/Daosavanh Thepsouvanh/Daosavanh.Thepsouvanh.jpg",
        "tags": "",
        "email": "daosavanh.thepsouvanh@intersec.com",
        "id": "daosavanh.thepsouvanh@intersec.com",
        "parentId": "nassim.mnafeg@intersec.com"
    },
    {
        "firstname": "Dimitri",
        "lastname": "Rivoire",
        "position": "Frontend Developer",
        "n+1": "alexis.brasy@intersec.com",
        "img": "intersecAmazingPeople/Dimitri Rivoire/Dimitri_RIVOIRE.jpg",
        "tags": "",
        "email": "dimitri.rivoire@intersec.com",
        "id": "dimitri.rivoire@intersec.com",
        "parentId": "alexis.brasy@intersec.com"
    },
    {
        "firstname": "Djaballah",
        "lastname": "Djedid",
        "position": "Developer",
        "n+1": "nassim.mnafeg@intersec.com",
        "img": "intersecAmazingPeople/Djaballah Djedid/Djaballah_DJEDID.jpg",
        "tags": "",
        "email": "djaballah.djedid@intersec.com",
        "id": "djaballah.djedid@intersec.com",
        "parentId": "nassim.mnafeg@intersec.com"
    },
    {
        "firstname": "Djamel-Eddine",
        "lastname": "Belghoul",
        "position": "Integration Engineer",
        "n+1": "emilien.coffin@intersec.com",
        "img": "intersecAmazingPeople/Djamel-Eddine Belghoul/Djamel.Eddine.Belghoul.jpg",
        "tags": "",
        "email": "djamel-eddine.belghoul@intersec.com",
        "id": "djamel-eddine.belghoul@intersec.com",
        "parentId": "emilien.coffin@intersec.com"
    },
    {
        "firstname": "Damien",
        "lastname": "Lemenager",
        "position": "Flutter Developer",
        "n+1": "alexis.brasy@intersec.com",
        "img": "intersecAmazingPeople/Damien Lemenager/Lemenager.Damien.jpg",
        "tags": "",
        "email": "damien.lemenager@intersec.com",
        "id": "damien.lemenager@intersec.com",
        "parentId": "alexis.brasy@intersec.com"
    },
    {
        "firstname": "Djibril",
        "lastname": "Faty",
        "position": "Support Engineer",
        "n+1": "onur.topcu@intersec.com",
        "img": "intersecAmazingPeople/Djibril Faty/FATY.Djibril.jpg",
        "tags": "",
        "email": "djibril.faty@intersec.com",
        "id": "djibril.faty@intersec.com",
        "parentId": "onur.topcu@intersec.com"
    },
    {
        "firstname": "Djamila",
        "lastname": "Bendjafar",
        "position": "Project Manager",
        "n+1": "emilien.coffin@intersec.com",
        "img": "intersecAmazingPeople/Djamila Bendjafar/Benjafar.Djamila.jpg",
        "tags": "",
        "email": "djamila.bendjafar@intersec.com",
        "id": "djamila.bendjafar@intersec.com",
        "parentId": "emilien.coffin@intersec.com"
    },
    {
        "firstname": "Elie",
        "lastname": "Duleu",
        "position": "C Developer",
        "n+1": "rawad.zgheib@intersec.com",
        "img": "intersecAmazingPeople/Elie Duleu/Elie.Duleu.jpg",
        "tags": "",
        "email": "elie.duleu@intersec.com",
        "id": "elie.duleu@intersec.com",
        "parentId": "rawad.zgheib@intersec.com"
    },
    {
        "firstname": "Elie",
        "lastname": "Hamawi",
        "position": "Integration Engineer",
        "n+1": "emilien.coffin@intersec.com",
        "img": "intersecAmazingPeople/Elie El Hamawi/Elie.ElHamawi.jpg",
        "tags": "",
        "email": "elie.hamawi@intersec.com",
        "id": "elie.hamawi@intersec.com",
        "parentId": "emilien.coffin@intersec.com"
    },
    {
        "firstname": "Emilien",
        "lastname": "Coffin",
        "position": "Leader of Integration Process",
        "n+1": "mohit.maheshwari@intersec.com",
        "img": "intersecAmazingPeople/Emilien Coffin/COFFIN.Emilien.JPG",
        "tags": "management",
        "email": "emilien.coffin@intersec.com",
        "id": "emilien.coffin@intersec.com",
        "parentId": "mohit.maheshwari@intersec.com"
    },
    {
        "firstname": "Fabien",
        "lastname": "Marchand",
        "position": "DevOps Engineer",
        "n+1": "jean-marc.coic@intersec.com",
        "img": "intersecAmazingPeople/Fabien Marchand/MARCHAND.Fabien.jpg",
        "tags": "",
        "email": "fabien.marchand@intersec.com",
        "id": "fabien.marchand@intersec.com",
        "parentId": "jean-marc.coic@intersec.com"
    },
    {
        "firstname": "Fanyo",
        "lastname": "Siliadin",
        "position": "Frontend Developer",
        "n+1": "alexis.brasy@intersec.com",
        "img": "intersecAmazingPeople/Fanyo Siliadin/Fanyo.Siliadin.jpg",
        "tags": "",
        "email": "fanyo.siliadin@intersec.com",
        "id": "fanyo.siliadin@intersec.com",
        "parentId": "alexis.brasy@intersec.com"
    },
    {
        "firstname": "Fehmi",
        "lastname": "Sanaa",
        "position": "Regional Sales Manager - Dubai",
        "n+1": "ahmed.hamza@intersec.com",
        "img": "intersecAmazingPeople/Fehmi Sanaa/Fehmi_SANAA.jpg",
        "tags": "",
        "email": "fehmi.sanaa@intersec.com",
        "id": "fehmi.sanaa@intersec.com",
        "parentId": "ahmed.hamza@intersec.com"
    },
    {
        "firstname": "Filip",
        "lastname": "Biljic",
        "position": "Integration Engineer",
        "n+1": "emilien.coffin@intersec.com",
        "img": "intersecAmazingPeople/Filip Biljic/Filip.Biljic.jpg",
        "tags": "",
        "email": "filip.biljic@intersec.com",
        "id": "filip.biljic@intersec.com",
        "parentId": "emilien.coffin@intersec.com"
    },
    {
        "firstname": "Frederic",
        "lastname": "Chauveau",
        "position": "C Developer",
        "n+1": "alexis.brasy@intersec.com",
        "img": "intersecAmazingPeople/Frederic Chauveau/Frederic.Chauveau.png",
        "tags": "",
        "email": "frederic.chauveau@intersec.com",
        "id": "frederic.chauveau@intersec.com",
        "parentId": "alexis.brasy@intersec.com"
    },
    {
        "firstname": "Frederic",
        "lastname": "Tutzo",
        "position": "Continuous Integrator",
        "n+1": "nassim.mnafeg@intersec.com",
        "img": "intersecAmazingPeople/Frederic Tutzo/fred.jpg",
        "tags": "",
        "email": "frederic.tutzo@intersec.com",
        "id": "frederic.tutzo@intersec.com",
        "parentId": "nassim.mnafeg@intersec.com"
    },
    {
        "firstname": "Gabriel",
        "lastname": "Terrien",
        "position": "Integration Engineer",
        "n+1": "matthias.granger@intersec.com",
        "img": "intersecAmazingPeople/Gabriel Terrien/terrien.gabriel.jpg",
        "tags": "",
        "email": "gabriel.terrien@intersec.com",
        "id": "gabriel.terrien@intersec.com",
        "parentId": "matthias.granger@intersec.com"
    },
    {
        "firstname": "Guillaume",
        "lastname": "Chevallerau",
        "position": "Software Architect",
        "n+1": "nassim.mnafeg@intersec.com",
        "img": "intersecAmazingPeople/Guillaume Chevallerau/chevallereau.guillaume.png",
        "tags": "",
        "email": "guillaume.chevallerau@intersec.com",
        "id": "guillaume.chevallerau@intersec.com",
        "parentId": "nassim.mnafeg@intersec.com"
    },
    {
        "firstname": "Guillaume",
        "lastname": "Renaud",
        "position": "Continuous Integrator",
        "n+1": "rawad.zgheib@intersec.com",
        "img": "intersecAmazingPeople/Guillaume Renaud/Guillaume.Renaud.jpg",
        "tags": "",
        "email": "guillaume.renaud@intersec.com",
        "id": "guillaume.renaud@intersec.com",
        "parentId": "rawad.zgheib@intersec.com"
    },
    {
        "firstname": "Hassina",
        "lastname": "Moulai",
        "position": "Developer",
        "n+1": "nassim.mnafeg@intersec.com",
        "img": "intersecAmazingPeople/Hassina Moulai/Hassina.Moulai.jpg",
        "tags": "",
        "email": "hassina.moulai@intersec.com",
        "id": "hassina.moulai@intersec.com",
        "parentId": "nassim.mnafeg@intersec.com"
    },
    {
        "firstname": "Haytham",
        "lastname": "Beshir",
        "position": "Program Manager",
        "n+1": "mohit.maheshwari@intersec.com",
        "img": "intersecAmazingPeople/Haytham Beshir/beshir.haytham.jpg",
        "tags": "management",
        "email": "haytham.beshir@intersec.com",
        "id": "haytham.beshir@intersec.com",
        "parentId": "mohit.maheshwari@intersec.com"
    },
    {
        "firstname": "Imad",
        "lastname": "Zidane",
        "position": "Solution Architect",
        "n+1": "nicolas.najman@intersec.com",
        "img": "intersecAmazingPeople/Imad Zidane/Imad_ZIDANE.jpg",
        "tags": "",
        "email": "imad.zidane@intersec.com",
        "id": "imad.zidane@intersec.com",
        "parentId": "nicolas.najman@intersec.com"
    },
    {
        "firstname": "Imen",
        "lastname": "Benabdallah",
        "position": "Continuous Integrator",
        "n+1": "alexis.brasy@intersec.com",
        "img": "intersecAmazingPeople/Imen Benabdallah/Imen_BENABDALLAH.jpg",
        "tags": "",
        "email": "imen.benabdallah@intersec.com",
        "id": "imen.benabdallah@intersec.com",
        "parentId": "alexis.brasy@intersec.com"
    },
    {
        "firstname": "Ingolf",
        "lastname": "Ruh",
        "position": "CRO",
        "n+1": "yann.chevalier@intersec.com",
        "img": "intersecAmazingPeople/Ingolf Ruh/RUH.Ingolf.jpg",
        "tags": "management",
        "email": "ingolf.ruh@intersec.com",
        "id": "ingolf.ruh@intersec.com",
        "parentId": "yann.chevalier@intersec.com"
    },
    {
        "firstname": "Isabelle",
        "lastname": "Granger",
        "position": "General Accountant",
        "n+1": "caroline.dumaitre@intersec.com",
        "img": "intersecAmazingPeople/Isabelle Granger/Granger.Isabelle.jpeg",
        "tags": "",
        "email": "isabelle.granger@intersec.com",
        "id": "isabelle.granger@intersec.com",
        "parentId": "caroline.dumaitre@intersec.com"
    },
    {
        "firstname": "Jean",
        "lastname": "Huber",
        "position": "Project Manager",
        "n+1": "emilien.coffin@intersec.com",
        "img": "intersecAmazingPeople/Jean Huber/Jean.Huber.png",
        "tags": "",
        "email": "jean.huber@intersec.com",
        "id": "jean.huber@intersec.com",
        "parentId": "emilien.coffin@intersec.com"
    },
    {
        "firstname": "Jean-Marc",
        "lastname": "Coic",
        "position": "CTO",
        "n+1": "yann.chevalier@intersec.com",
        "img": "intersecAmazingPeople/Jean-Marc Coic/COIC.Jean-Marc.jpg",
        "tags": "management",
        "email": "jean-marc.coic@intersec.com",
        "id": "jean-marc.coic@intersec.com",
        "parentId": "yann.chevalier@intersec.com"
    },
    {
        "firstname": "Jeremy",
        "lastname": "Caradec",
        "position": "C Developer",
        "n+1": "rawad.zgheib@intersec.com",
        "img": "intersecAmazingPeople/Jeremy Caradec/Caradec.Jeremy.png",
        "tags": "",
        "email": "jeremy.caradec@intersec.com",
        "id": "jeremy.caradec@intersec.com",
        "parentId": "rawad.zgheib@intersec.com"
    },
    {
        "firstname": "Jonas",
        "lastname": "Prieur",
        "position": "Integration Engineer",
        "n+1": "simon.ravier@intersec.com",
        "img": "intersecAmazingPeople/Jonas Prieur/Jonas.PRIEUR.jpg",
        "tags": "",
        "email": "jonas.prieur@intersec.com",
        "id": "jonas.prieur@intersec.com",
        "parentId": "simon.ravier@intersec.com"
    },
    {
        "firstname": "Jerome",
        "lastname": "Levol",
        "position": "Integration Engineer",
        "n+1": "emilien.coffin@intersec.com",
        "img": "intersecAmazingPeople/Jerome Levol/Jerome.Levol.jpg",
        "tags": "",
        "email": "jerome.levol@intersec.com",
        "id": "jerome.levol@intersec.com",
        "parentId": "emilien.coffin@intersec.com"
    },
    {
        "firstname": "Kamal",
        "lastname": "Fadlaoui",
        "position": "VP Engineering",
        "n+1": "jean-marc.coic@intersec.com",
        "img": "intersecAmazingPeople/Kamal Fadlaoui/Fadlaoui.Kamal.jpg",
        "tags": "management",
        "email": "kamal.fadlaoui@intersec.com",
        "id": "kamal.fadlaoui@intersec.com",
        "parentId": "jean-marc.coic@intersec.com"
    },
    {
        "firstname": "Jonathan",
        "lastname": "Squirawski",
        "position": "Software Architect",
        "n+1": "jean-marc.coic@intersec.com",
        "img": "intersecAmazingPeople/Jonathan Squirawski/Jonathan_Squirawski.jpg",
        "tags": "",
        "email": "jonathan.squirawski@intersec.com",
        "id": "jonathan.squirawski@intersec.com",
        "parentId": "jean-marc.coic@intersec.com"
    },
    {
        "firstname": "Kamel",
        "lastname": "Majdoub",
        "position": "Recruitment Manager",
        "n+1": "oyo.ndoro@intersec.com",
        "img": "intersecAmazingPeople/Kamel Majdoub/majdoub.kamel.png",
        "tags": "",
        "email": "kamel.majdoub@intersec.com",
        "id": "kamel.majdoub@intersec.com",
        "parentId": "oyo.ndoro@intersec.com"
    },
    {
        "firstname": "Kevin",
        "lastname": "Champion",
        "position": "IT Manager",
        "n+1": "clement.vandoolaeghe@intersec.com",
        "img": "intersecAmazingPeople/Kevin Champion/Kevin_Champion.jpg",
        "tags": "",
        "email": "kevin.champion@intersec.com",
        "id": "kevin.champion@intersec.com",
        "parentId": "clement.vandoolaeghe@intersec.com"
    },
    {
        "firstname": "Kurian",
        "lastname": "Manjakkal",
        "position": "VP Sales",
        "n+1": "ingolf.ruh@intersec.com",
        "img": "intersecAmazingPeople/Kurian Manjakkal/Manjakkal.Kurian.jpg",
        "tags": "management",
        "email": "kurian.manjakkal@intersec.com",
        "id": "kurian.manjakkal@intersec.com",
        "parentId": "ingolf.ruh@intersec.com"
    },
    {
        "firstname": "Emmanuel",
        "lastname": "Cousin",
        "position": "C Developer",
        "n+1": "rawad.zgheib@intersec.com",
        "img": "intersecAmazingPeople/Emmanuel Cousin/COUSIN.Emmanuel.JPG",
        "tags": "",
        "email": "emmanuel.cousin@intersec.com",
        "id": "emmanuel.cousin@intersec.com",
        "parentId": "rawad.zgheib@intersec.com"
    },
    {
        "firstname": "Killian",
        "lastname": "Goff",
        "position": "Data Scientist",
        "n+1": "pierre-louis.cuny@intersec.com",
        "img": "intersecAmazingPeople/Killian Le Goff/Killian_LeGoff.jpg",
        "tags": "",
        "email": "killian.goff@intersec.com",
        "id": "killian.goff@intersec.com",
        "parentId": "pierre-louis.cuny@intersec.com"
    },
    {
        "firstname": "Latifa",
        "lastname": "Chalouati",
        "position": "Integration Engineer",
        "n+1": "emilien.coffin@intersec.com",
        "img": "intersecAmazingPeople/Latifa Chalouati/Latifa_Chalouati.jpg",
        "tags": "",
        "email": "latifa.chalouati@intersec.com",
        "id": "latifa.chalouati@intersec.com",
        "parentId": "emilien.coffin@intersec.com"
    },
    {
        "firstname": "Mahdi",
        "lastname": "Said",
        "position": "Integration Engineer (TN)",
        "n+1": "mohit.maheshwari@intersec.com",
        "img": "",
        "tags": "",
        "email": "mahdi.said@intersec.com",
        "id": "mahdi.said@intersec.com",
        "parentId": "mohit.maheshwari@intersec.com"
    },
    {
        "firstname": "Maja",
        "lastname": "Lazarevska",
        "position": "Project Manager",
        "n+1": "emilien.coffin@intersec.com",
        "img": "intersecAmazingPeople/Maja Lazarevska/Lazarevska.Maja.jpg",
        "tags": "",
        "email": "maja.lazarevska@intersec.com",
        "id": "maja.lazarevska@intersec.com",
        "parentId": "emilien.coffin@intersec.com"
    },
    {
        "firstname": "Marie-Luna",
        "lastname": "Gonzalez",
        "position": "Marketing and Social Networking Apprentice",
        "n+1": "charlotte.cardona@intersec.com",
        "img": "intersecAmazingPeople/Marie-Luna Gonzalez/Marie.Luna.Gonzalez.jpg",
        "tags": "",
        "email": "marie-luna.gonzalez@intersec.com",
        "id": "marie-luna.gonzalez@intersec.com",
        "parentId": "charlotte.cardona@intersec.com"
    },
    {
        "firstname": "Marion",
        "lastname": "Biancale",
        "position": "Continuous Integrator",
        "n+1": "rawad.zgheib@intersec.com",
        "img": "intersecAmazingPeople/Marion Biancale/Biancale.Marion.jpg",
        "tags": "",
        "email": "marion.biancale@intersec.com",
        "id": "marion.biancale@intersec.com",
        "parentId": "rawad.zgheib@intersec.com"
    },
    {
        "firstname": "Marion",
        "lastname": "Larsen",
        "position": "Frontend Developer",
        "n+1": "alexis.brasy@intersec.com",
        "img": "intersecAmazingPeople/Marion Larsen/Mario.Larsen.jpg",
        "tags": "",
        "email": "marion.larsen@intersec.com",
        "id": "marion.larsen@intersec.com",
        "parentId": "alexis.brasy@intersec.com"
    },
    {
        "firstname": "Mathieu",
        "lastname": "Vallet",
        "position": "C Developer",
        "n+1": "rawad.zgheib@intersec.com",
        "img": "intersecAmazingPeople/Mathieu Vallet/Vallet.Mathieu.jpg",
        "tags": "",
        "email": "mathieu.vallet@intersec.com",
        "id": "mathieu.vallet@intersec.com",
        "parentId": "rawad.zgheib@intersec.com"
    },
    {
        "firstname": "Marwane",
        "lastname": "Akram",
        "position": "Product Owner",
        "n+1": "kamal.fadlaoui@intersec.com",
        "img": "intersecAmazingPeople/Marwane Akram/AKRAM.Marwane.jpg",
        "tags": "",
        "email": "marwane.akram@intersec.com",
        "id": "marwane.akram@intersec.com",
        "parentId": "kamal.fadlaoui@intersec.com"
    },
    {
        "firstname": "Mathieu",
        "lastname": "Haydar",
        "position": "Continuous Integrator",
        "n+1": "alexis.brasy@intersec.com",
        "img": "intersecAmazingPeople/Mathieu Abou Haydar/Mathieu_ABOU-HAYDAR.jpg",
        "tags": "",
        "email": "mathieu.haydar@intersec.com",
        "id": "mathieu.haydar@intersec.com",
        "parentId": "alexis.brasy@intersec.com"
    },
    {
        "firstname": "Matthias",
        "lastname": "Granger",
        "position": "Project Manager & Regional TL",
        "n+1": "mohit.maheshwari@intersec.com",
        "img": "intersecAmazingPeople/Matthias Granger/granger.matthias.jpg",
        "tags": "management",
        "email": "matthias.granger@intersec.com",
        "id": "matthias.granger@intersec.com",
        "parentId": "mohit.maheshwari@intersec.com"
    },
    {
        "firstname": "Maxime",
        "lastname": "Leblanc",
        "position": "C Developer",
        "n+1": "nassim.mnafeg@intersec.com",
        "img": "intersecAmazingPeople/Maxime Leblanc/Maxime_Leblanc.jpg",
        "tags": "",
        "email": "maxime.leblanc@intersec.com",
        "id": "maxime.leblanc@intersec.com",
        "parentId": "nassim.mnafeg@intersec.com"
    },
    {
        "firstname": "Matthieu",
        "lastname": "Michelet",
        "position": "Site Reliability Engineer",
        "n+1": "clement.vandoolaeghe@intersec.com",
        "img": "intersecAmazingPeople/Matthieu Michelet/matthieu_michelet.jpg",
        "tags": "",
        "email": "matthieu.michelet@intersec.com",
        "id": "matthieu.michelet@intersec.com",
        "parentId": "clement.vandoolaeghe@intersec.com"
    },
    {
        "firstname": "Meryam",
        "lastname": "Azaiez",
        "position": "Integration Engineer (TN)",
        "n+1": "mohit.maheshwari@intersec.com",
        "img": "intersecAmazingPeople/Meryam Azaiez/Meryam_Azaiez.jpg",
        "tags": "",
        "email": "meryam.azaiez@intersec.com",
        "id": "meryam.azaiez@intersec.com",
        "parentId": "mohit.maheshwari@intersec.com"
    },
    {
        "firstname": "Mohamad",
        "lastname": "Dib",
        "position": "Integration Engineer",
        "n+1": "haytham.beshir@intersec.com",
        "img": "intersecAmazingPeople/Mohamad Dib/dib.mohamad.png",
        "tags": "",
        "email": "mohamad.dib@intersec.com",
        "id": "mohamad.dib@intersec.com",
        "parentId": "haytham.beshir@intersec.com"
    },
    {
        "firstname": "Mohamed",
        "lastname": "Aboelnoor",
        "position": "Integration Engineer (Egypt)",
        "n+1": "neeraj.bhatnagar@intersec.com",
        "img": "intersecAmazingPeople/Mohamed Aboelnoor/Aboelnoo.Mohamed.png",
        "tags": "",
        "email": "mohamed.aboelnoor@intersec.com",
        "id": "mohamed.aboelnoor@intersec.com",
        "parentId": "neeraj.bhatnagar@intersec.com"
    },
    {
        "firstname": "Mohamed",
        "lastname": "Sulaiman",
        "position": "Solution Architect",
        "n+1": "nicolas.najman@intersec.com",
        "img": "intersecAmazingPeople/Mohamed Yousuf Sulaiman/Mohamed.Yousuf.jpg",
        "tags": "",
        "email": "mohamed.sulaiman@intersec.com",
        "id": "mohamed.sulaiman@intersec.com",
        "parentId": "nicolas.najman@intersec.com"
    },
    {
        "firstname": "Mohamed",
        "lastname": "Kahlal",
        "position": "VP Engineering Delivery",
        "n+1": "jean-marc.coic@intersec.com",
        "img": "intersecAmazingPeople/Mohamed Kahlal/KAHLAL.mohamed.png",
        "tags": "management",
        "email": "mohamed.kahlal@intersec.com",
        "id": "mohamed.kahlal@intersec.com",
        "parentId": "jean-marc.coic@intersec.com"
    },
    {
        "firstname": "Mohammed",
        "lastname": "Abbas",
        "position": "Presales",
        "n+1": "ingolf.ruh@intersec.com",
        "img": "intersecAmazingPeople/Mohammed Abbas/Mohamed.Abas.jpg",
        "tags": "",
        "email": "mohammed.abbas@intersec.com",
        "id": "mohammed.abbas@intersec.com",
        "parentId": "ingolf.ruh@intersec.com"
    },
    {
        "firstname": "Mohit",
        "lastname": "Maheshwari",
        "position": "VP Operations",
        "n+1": "yann.chevalier@intersec.com",
        "img": "intersecAmazingPeople/Mohit Maheshwari/Maheshwari.Mohit.jpg",
        "tags": "management",
        "email": "mohit.maheshwari@intersec.com",
        "id": "mohit.maheshwari@intersec.com",
        "parentId": "yann.chevalier@intersec.com"
    },
    {
        "firstname": "Muyao",
        "lastname": "Chen",
        "position": "C Developer",
        "n+1": "alexis.brasy@intersec.com",
        "img": "intersecAmazingPeople/Muyao Chen/Muyao.Chen.jpg",
        "tags": "",
        "email": "muyao.chen@intersec.com",
        "id": "muyao.chen@intersec.com",
        "parentId": "alexis.brasy@intersec.com"
    },
    {
        "firstname": "Mouna",
        "lastname": "Benzaroual",
        "position": "Sales Administration Manager",
        "n+1": "nicolas.dumarcet@intersec.com",
        "img": "intersecAmazingPeople/Mouna Benzaroual/Mouna.Benzaroual.jpg",
        "tags": "",
        "email": "mouna.benzaroual@intersec.com",
        "id": "mouna.benzaroual@intersec.com",
        "parentId": "nicolas.dumarcet@intersec.com"
    },
    {
        "firstname": "Nadia",
        "lastname": "Traore",
        "position": "Project Manager",
        "n+1": "emilien.coffin@intersec.com",
        "img": "intersecAmazingPeople/Nadia Traore/nadia.jpg",
        "tags": "",
        "email": "nadia.traore@intersec.com",
        "id": "nadia.traore@intersec.com",
        "parentId": "emilien.coffin@intersec.com"
    },
    {
        "firstname": "Naveen",
        "lastname": "Kumar",
        "position": "Solution Architect - DUBAI",
        "n+1": "neeraj.bhatnagar@intersec.com",
        "img": "intersecAmazingPeople/Naveen Kumar/Naveen_KUMAR.jpg",
        "tags": "",
        "email": "naveen.kumar@intersec.com",
        "id": "naveen.kumar@intersec.com",
        "parentId": "neeraj.bhatnagar@intersec.com"
    },
    {
        "firstname": "Nahin",
        "lastname": "Musarrat",
        "position": "Integration Engineer",
        "n+1": "mohit.maheshwari@intersec.com",
        "img": "intersecAmazingPeople/Nahin Musarrat/Nahin.Musarrat.png",
        "tags": "",
        "email": "nahin.musarrat@intersec.com",
        "id": "nahin.musarrat@intersec.com",
        "parentId": "mohit.maheshwari@intersec.com"
    },
    {
        "firstname": "Nassim",
        "lastname": "Mnafeg",
        "position": "Team Leader",
        "n+1": "mohamed.kahlal@intersec.com",
        "img": "intersecAmazingPeople/Nassim Mnafeg/Nassim_MNAFEG.jpg",
        "tags": "",
        "email": "nassim.mnafeg@intersec.com",
        "id": "nassim.mnafeg@intersec.com",
        "parentId": "mohamed.kahlal@intersec.com"
    },
    {
        "firstname": "Nawaal",
        "lastname": "Mamadou",
        "position": "Support Engineer",
        "n+1": "onur.topcu@intersec.com",
        "img": "intersecAmazingPeople/Nawaal Mamadou/MAMADOU.Nawaal.jpg",
        "tags": "",
        "email": "nawaal.mamadou@intersec.com",
        "id": "nawaal.mamadou@intersec.com",
        "parentId": "onur.topcu@intersec.com"
    },
    {
        "firstname": "Djamel-Eddine",
        "lastname": "Meharga",
        "position": "Developer",
        "n+1": "alexis.brasy@intersec.com",
        "img": "intersecAmazingPeople/Djamel-Eddine Meharga/Meharga.Djamel.jpg",
        "tags": "",
        "email": "djamel-eddine.meharga@intersec.com",
        "id": "djamel-eddine.meharga@intersec.com",
        "parentId": "alexis.brasy@intersec.com"
    },
    {
        "firstname": "Neeraj",
        "lastname": "Bhatnagar",
        "position": "Project Manager",
        "n+1": "mohit.maheshwari@intersec.com",
        "img": "intersecAmazingPeople/Neeraj Bhatnagar/Neeraj_BHATNAGAR.jpg",
        "tags": "management",
        "email": "neeraj.bhatnagar@intersec.com",
        "id": "neeraj.bhatnagar@intersec.com",
        "parentId": "mohit.maheshwari@intersec.com"
    },
    {
        "firstname": "Antoine",
        "lastname": "Loheac",
        "position": "C Developer",
        "n+1": "rawad.zgheib@intersec.com",
        "img": "intersecAmazingPeople/Antoine Loheac/loheac.antoine.png",
        "tags": "",
        "email": "antoine.loheac@intersec.com",
        "id": "antoine.loheac@intersec.com",
        "parentId": "rawad.zgheib@intersec.com"
    },
    {
        "firstname": "Amer",
        "lastname": "Bdeoui",
        "position": "Product Owner",
        "n+1": "kamal.fadlaoui@intersec.com",
        "img": "intersecAmazingPeople/Amer Bdeoui/Bdoui.Amer.png",
        "tags": "",
        "email": "amer.bdeoui@intersec.com",
        "id": "amer.bdeoui@intersec.com",
        "parentId": "kamal.fadlaoui@intersec.com"
    },
    {
        "firstname": "Nicolas",
        "lastname": "Angevelle",
        "position": "DevOps Engineer",
        "n+1": "jean-marc.coic@intersec.com",
        "img": "intersecAmazingPeople/Nicolas Angevelle/ANGEVELLE.Nicolas.JPG",
        "tags": "",
        "email": "nicolas.angevelle@intersec.com",
        "id": "nicolas.angevelle@intersec.com",
        "parentId": "jean-marc.coic@intersec.com"
    },
    {
        "firstname": "Nicolas",
        "lastname": "Haddad",
        "position": "Regional Sales Manager",
        "n+1": "arnaud.westphal@intersec.com",
        "img": "intersecAmazingPeople/Nicolas Haddad/haddad.Nicolas.jpg",
        "tags": "",
        "email": "nicolas.haddad@intersec.com",
        "id": "nicolas.haddad@intersec.com",
        "parentId": "arnaud.westphal@intersec.com"
    },
    {
        "firstname": "Nicolas",
        "lastname": "Legrand",
        "position": "Support Engineer",
        "n+1": "onur.topcu@intersec.com",
        "img": "intersecAmazingPeople/Nicolas Legrand/LEGRAND.Nicolas.JPG",
        "tags": "",
        "email": "nicolas.legrand@intersec.com",
        "id": "nicolas.legrand@intersec.com",
        "parentId": "onur.topcu@intersec.com"
    },
    {
        "firstname": "Nicolas",
        "lastname": "Najman",
        "position": "SA Director",
        "n+1": "mohit.maheshwari@intersec.com",
        "img": "intersecAmazingPeople/Nicolas Najman/najman.nicolas.png",
        "tags": "management",
        "email": "nicolas.najman@intersec.com",
        "id": "nicolas.najman@intersec.com",
        "parentId": "mohit.maheshwari@intersec.com"
    },
    {
        "firstname": "Nicolas",
        "lastname": "Pauss",
        "position": "Software Architect",
        "n+1": "alexis.brasy@intersec.com",
        "img": "intersecAmazingPeople/Nicolas Pauss/PAUSS.nicolas.JPG",
        "tags": "",
        "email": "nicolas.pauss@intersec.com",
        "id": "nicolas.pauss@intersec.com",
        "parentId": "alexis.brasy@intersec.com"
    },
    {
        "firstname": "Nicolas",
        "lastname": "Rousseau-Dumarcet",
        "position": "CFO",
        "n+1": "yann.chevalier@intersec.com",
        "img": "intersecAmazingPeople/Nicolas Rousseau-Dumarcet/Nicolas.Rousseau-Dumarcet.jpg",
        "tags": "management",
        "email": "nicolas.rousseau-dumarcet@intersec.com",
        "id": "nicolas.rousseau-dumarcet@intersec.com",
        "parentId": "yann.chevalier@intersec.com"
    },
    {
        "firstname": "Nicolas",
        "lastname": "Sery",
        "position": "System administrator",
        "n+1": "clement.vandoolaeghe@intersec.com",
        "img": "intersecAmazingPeople/Nicolas Sery/Nicolas.Sery.jpg",
        "tags": "",
        "email": "nicolas.sery@intersec.com",
        "id": "nicolas.sery@intersec.com",
        "parentId": "clement.vandoolaeghe@intersec.com"
    },
    {
        "firstname": "Nikola",
        "lastname": "Milic",
        "position": "Support Engineer",
        "n+1": "onur.topcu@intersec.com",
        "img": "",
        "tags": "",
        "email": "nikola.milic@intersec.com",
        "id": "nikola.milic@intersec.com",
        "parentId": "onur.topcu@intersec.com"
    },
    {
        "firstname": "Oceane",
        "lastname": "Boudinet",
        "position": "Technical Documentation Writer",
        "n+1": "christele.camara@intersec.com",
        "img": "intersecAmazingPeople/Oceane Boudinet/Oceane_BOUDINET.jpg",
        "tags": "",
        "email": "oceane.boudinet@intersec.com",
        "id": "oceane.boudinet@intersec.com",
        "parentId": "christele.camara@intersec.com"
    },
    {
        "firstname": "Onur",
        "lastname": "Topcu",
        "position": "Support Manager",
        "n+1": "mohit.maheshwari@intersec.com",
        "img": "intersecAmazingPeople/Onur Topcu/Topcu.Onur.png",
        "tags": "management",
        "email": "onur.topcu@intersec.com",
        "id": "onur.topcu@intersec.com",
        "parentId": "mohit.maheshwari@intersec.com"
    },
    {
        "firstname": "Pierre-Louis",
        "lastname": "Cuny",
        "position": "Data Science Team Lead",
        "n+1": "jean-marc.coic@intersec.com",
        "img": "intersecAmazingPeople/Pierre-Louis Cuny/CUNY.Pierre-Louis.jpg",
        "tags": "",
        "email": "pierre-louis.cuny@intersec.com",
        "id": "pierre-louis.cuny@intersec.com",
        "parentId": "jean-marc.coic@intersec.com"
    },
    {
        "firstname": "Nicolas",
        "lastname": "Delaunay",
        "position": "Regional Sales Manager",
        "n+1": "arnaud.westphal@intersec.com",
        "img": "intersecAmazingPeople/Nicolas Delaunay/Delaunay.Nicolas.jpg",
        "tags": "",
        "email": "nicolas.delaunay@intersec.com",
        "id": "nicolas.delaunay@intersec.com",
        "parentId": "arnaud.westphal@intersec.com"
    },
    {
        "firstname": "Preeti",
        "lastname": "Aggarwal",
        "position": "Managed Service Expert - DUBAI",
        "n+1": "haytham.beshir@intersec.com",
        "img": "intersecAmazingPeople/Preeti Aggarwal/Preeti_AGGARWAL.jpg",
        "tags": "",
        "email": "preeti.aggarwal@intersec.com",
        "id": "preeti.aggarwal@intersec.com",
        "parentId": "haytham.beshir@intersec.com"
    },
    {
        "firstname": "Rawad",
        "lastname": "Zgheib",
        "position": "Team Leader",
        "n+1": "mohamed.kahlal@intersec.com",
        "img": "intersecAmazingPeople/Rawad Zgheib/Rawad_Zgheib.png",
        "tags": "",
        "email": "rawad.zgheib@intersec.com",
        "id": "rawad.zgheib@intersec.com",
        "parentId": "mohamed.kahlal@intersec.com"
    },
    {
        "firstname": "Reshmi",
        "lastname": "Anand",
        "position": "Integration Engineer",
        "n+1": "emilien.coffin@intersec.com",
        "img": "intersecAmazingPeople/Reshmi Anand/Reshmi.Anand.jpg",
        "tags": "",
        "email": "reshmi.anand@intersec.com",
        "id": "reshmi.anand@intersec.com",
        "parentId": "emilien.coffin@intersec.com"
    },
    {
        "firstname": "Rkia",
        "lastname": "Hatif",
        "position": "Payroll and Administrative Manager",
        "n+1": "oyo.ndoro@intersec.com",
        "img": "intersecAmazingPeople/Rkia Hatif/hatif.rkia.png",
        "tags": "",
        "email": "rkia.hatif@intersec.com",
        "id": "rkia.hatif@intersec.com",
        "parentId": "oyo.ndoro@intersec.com"
    },
    {
        "firstname": "Romain",
        "lastname": "Godais",
        "position": "Software Architect",
        "n+1": "nassim.mnafeg@intersec.com",
        "img": "intersecAmazingPeople/Romain Le Godais/legodais.romain.jpg",
        "tags": "",
        "email": "romain.godais@intersec.com",
        "id": "romain.godais@intersec.com",
        "parentId": "nassim.mnafeg@intersec.com"
    },
    {
        "firstname": "Safwan",
        "lastname": "Alwan",
        "position": "C Developer",
        "n+1": "rawad.zgheib@intersec.com",
        "img": "intersecAmazingPeople/Safwan Alwan/Alwane.Safwan.jpg",
        "tags": "",
        "email": "safwan.alwan@intersec.com",
        "id": "safwan.alwan@intersec.com",
        "parentId": "rawad.zgheib@intersec.com"
    },
    {
        "firstname": "Samy",
        "lastname": "Kammoun",
        "position": "Recruitment Assistant",
        "n+1": "kamel.majdoub@intersec.com",
        "img": "intersecAmazingPeople/Samy Kammoun/Samy.Kammoun.jpg",
        "tags": "",
        "email": "samy.kammoun@intersec.com",
        "id": "samy.kammoun@intersec.com",
        "parentId": "kamel.majdoub@intersec.com"
    },
    {
        "firstname": "Sanh",
        "lastname": "Nguyen",
        "position": "Senior FP&A Analyst",
        "n+1": "nicolas.dumarcet@intersec.com",
        "img": "intersecAmazingPeople/Sanh Nguyen/Sanh_NGUYEN.jpg",
        "tags": "",
        "email": "sanh.nguyen@intersec.com",
        "id": "sanh.nguyen@intersec.com",
        "parentId": "nicolas.dumarcet@intersec.com"
    },
    {
        "firstname": "Sarra",
        "lastname": "Slimen",
        "position": "HR Assistant",
        "n+1": "rkia.hatif@intersec.com",
        "img": "intersecAmazingPeople/Sarra Ben Slimen/Sara.Ben.Slimane.jpg",
        "tags": "",
        "email": "sarra.slimen@intersec.com",
        "id": "sarra.slimen@intersec.com",
        "parentId": "rkia.hatif@intersec.com"
    },
    {
        "firstname": "Sebastien",
        "lastname": "Synold",
        "position": "Product Manager",
        "n+1": "christophe.nez@intersec.com",
        "img": "intersecAmazingPeople/Sebastien Synold/Sebastien_SYNOLD.jpg",
        "tags": "",
        "email": "sebastien.synold@intersec.com",
        "id": "sebastien.synold@intersec.com",
        "parentId": "christophe.nez@intersec.com"
    },
    {
        "firstname": "Segolene",
        "lastname": "Tutzo",
        "position": "Frontend Developer",
        "n+1": "nassim.mnafeg@intersec.com",
        "img": "intersecAmazingPeople/Segolene Tutzo/Segolene_TUTZO.jpg",
        "tags": "",
        "email": "segolene.tutzo@intersec.com",
        "id": "segolene.tutzo@intersec.com",
        "parentId": "nassim.mnafeg@intersec.com"
    },
    {
        "firstname": "Sebastien",
        "lastname": "Thouement",
        "position": "Software Architect",
        "n+1": "jean-marc.coic@intersec.com",
        "img": "intersecAmazingPeople/Sebastien Thouement/seb.jpg",
        "tags": "",
        "email": "sebastien.thouement@intersec.com",
        "id": "sebastien.thouement@intersec.com",
        "parentId": "jean-marc.coic@intersec.com"
    },
    {
        "firstname": "Shabab",
        "lastname": "Vadakkangara",
        "position": "Support Engineer (Dubai)",
        "n+1": "onur.topcu@intersec.com",
        "img": "intersecAmazingPeople/Shabab Vadakkangara/Shabab.Vadakkangara.jpg",
        "tags": "",
        "email": "shabab.vadakkangara@intersec.com",
        "id": "shabab.vadakkangara@intersec.com",
        "parentId": "onur.topcu@intersec.com"
    },
    {
        "firstname": "Simon",
        "lastname": "Bree",
        "position": "Site Reliability Engineer",
        "n+1": "clement.vandoolaeghe@intersec.com",
        "img": "intersecAmazingPeople/Simon Bree/Bree.simon.jpg",
        "tags": "",
        "email": "simon.bree@intersec.com",
        "id": "simon.bree@intersec.com",
        "parentId": "clement.vandoolaeghe@intersec.com"
    },
    {
        "firstname": "Simon",
        "lastname": "Ravier",
        "position": "Integration Technical Lead",
        "n+1": "mohit.maheshwari@intersec.com",
        "img": "intersecAmazingPeople/Simon Ravier/Ravier.Simon.png",
        "tags": "",
        "email": "simon.ravier@intersec.com",
        "id": "simon.ravier@intersec.com",
        "parentId": "mohit.maheshwari@intersec.com"
    },
    {
        "firstname": "Simone",
        "lastname": "Moreno",
        "position": "Continuous Integrator",
        "n+1": "rawad.zgheib@intersec.com",
        "img": "intersecAmazingPeople/Simone Moreno/MORENO.Simone.jpg",
        "tags": "",
        "email": "simone.moreno@intersec.com",
        "id": "simone.moreno@intersec.com",
        "parentId": "rawad.zgheib@intersec.com"
    },
    {
        "firstname": "Sirine",
        "lastname": "Ibrahim",
        "position": "Integration Engineer",
        "n+1": "emilien.coffin@intersec.com",
        "img": "intersecAmazingPeople/Sirine Ibrahim/Ibrahim.Sirine.png",
        "tags": "",
        "email": "sirine.ibrahim@intersec.com",
        "id": "sirine.ibrahim@intersec.com",
        "parentId": "emilien.coffin@intersec.com"
    },
    {
        "firstname": "Skander",
        "lastname": "Souidane",
        "position": "Tiger Program Manager",
        "n+1": "mohit.maheshwari@intersec.com",
        "img": "intersecAmazingPeople/Skander Souidane/SOUIDANE.Skander.jpg",
        "tags": "",
        "email": "skander.souidane@intersec.com",
        "id": "skander.souidane@intersec.com",
        "parentId": "mohit.maheshwari@intersec.com"
    },
    {
        "firstname": "Sneha",
        "lastname": "Dhotre",
        "position": "Integration Engineer",
        "n+1": "matthias.granger@intersec.com",
        "img": "intersecAmazingPeople/Sneha Dhotre/Sneha_DHOTRE.png",
        "tags": "",
        "email": "sneha.dhotre@intersec.com",
        "id": "sneha.dhotre@intersec.com",
        "parentId": "matthias.granger@intersec.com"
    },
    {
        "firstname": "Stephane",
        "lastname": "Jutras",
        "position": "Presales",
        "n+1": "ingolf.ruh@intersec.com",
        "img": "intersecAmazingPeople/Stephane Jutras/steph.jpg",
        "tags": "",
        "email": "stephane.jutras@intersec.com",
        "id": "stephane.jutras@intersec.com",
        "parentId": "ingolf.ruh@intersec.com"
    },
    {
        "firstname": "Souad",
        "lastname": "Touil",
        "position": "Regional Sales Director",
        "n+1": "arnaud.westphal@intersec.com",
        "img": "intersecAmazingPeople/Souad Touil/TOUIL.Souad.JPG",
        "tags": "",
        "email": "souad.touil@intersec.com",
        "id": "souad.touil@intersec.com",
        "parentId": "arnaud.westphal@intersec.com"
    },
    {
        "firstname": "Stephane",
        "lastname": "Richard",
        "position": "C Developer",
        "n+1": "alexis.brasy@intersec.com",
        "img": "intersecAmazingPeople/Stephane Richard/steph.jpg",
        "tags": "",
        "email": "stephane.richard@intersec.com",
        "id": "stephane.richard@intersec.com",
        "parentId": "alexis.brasy@intersec.com"
    },
    {
        "firstname": "Tarek",
        "lastname": "Tarawneh",
        "position": "Presales",
        "n+1": "ingolf.ruh@intersec.com",
        "img": "intersecAmazingPeople/Tarek Al Tarawneh/Tarawneh.Tarek.png",
        "tags": "",
        "email": "tarek.tarawneh@intersec.com",
        "id": "tarek.tarawneh@intersec.com",
        "parentId": "ingolf.ruh@intersec.com"
    },
    {
        "firstname": "Thomas",
        "lastname": "Graham-Wood",
        "position": "Marketing and Communication Specialist",
        "n+1": "charlotte.cardona@intersec.com",
        "img": "intersecAmazingPeople/Thomas Graham-Wood/Thomas_GRAHAM-WOOD.jpg",
        "tags": "",
        "email": "thomas.graham-wood@intersec.com",
        "id": "thomas.graham-wood@intersec.com",
        "parentId": "charlotte.cardona@intersec.com"
    },
    {
        "firstname": "Thomas",
        "lastname": "Marquis",
        "position": "Regional Sales Manager",
        "n+1": "arnaud.westphal@intersec.com",
        "img": "intersecAmazingPeople/Thomas Marquis/Marquis.Thomas.jpg",
        "tags": "",
        "email": "thomas.marquis@intersec.com",
        "id": "thomas.marquis@intersec.com",
        "parentId": "arnaud.westphal@intersec.com"
    },
    {
        "firstname": "Tom",
        "lastname": "Mcewan",
        "position": "Regional Sales Manager",
        "n+1": "ingolf.ruh@intersec.com",
        "img": "intersecAmazingPeople/Tom Mcewan/mcewan.Tom.JPG",
        "tags": "",
        "email": "tom.mcewan@intersec.com",
        "id": "tom.mcewan@intersec.com",
        "parentId": "ingolf.ruh@intersec.com"
    },
    {
        "firstname": "Victorien",
        "lastname": "Serre",
        "position": "Support Engineer",
        "n+1": "onur.topcu@intersec.com",
        "img": "",
        "tags": "",
        "email": "victorien.serre@intersec.com",
        "id": "victorien.serre@intersec.com",
        "parentId": "onur.topcu@intersec.com"
    },
    {
        "firstname": "Vincent",
        "lastname": "Mas",
        "position": "Product Owner",
        "n+1": "kamal.fadlaoui@intersec.com",
        "img": "intersecAmazingPeople/Vincent Mas/Mas.Vincent.png",
        "tags": "",
        "email": "vincent.mas@intersec.com",
        "id": "vincent.mas@intersec.com",
        "parentId": "kamal.fadlaoui@intersec.com"
    },
    {
        "firstname": "Xavier",
        "lastname": "Afyouni",
        "position": "IT Trainer",
        "n+1": "emilien.coffin@intersec.com",
        "img": "intersecAmazingPeople/Xavier Afyouni/Xavier_AFYOUNI.jpg",
        "tags": "",
        "email": "xavier.afyouni@intersec.com",
        "id": "xavier.afyouni@intersec.com",
        "parentId": "emilien.coffin@intersec.com"
    },
    {
        "firstname": "Walid",
        "lastname": "Kaddour",
        "position": "Solution Architect (TN)",
        "n+1": "nicolas.najman@intersec.com",
        "img": "intersecAmazingPeople/Walid Kaddour/Walid_Kaddour.jpg",
        "tags": "",
        "email": "walid.kaddour@intersec.com",
        "id": "walid.kaddour@intersec.com",
        "parentId": "nicolas.najman@intersec.com"
    },
    {
        "firstname": "Xavier",
        "lastname": "Chantry",
        "position": "Software Architect",
        "n+1": "rawad.zgheib@intersec.com",
        "img": "intersecAmazingPeople/Xavier Chantry/CHANTRY.xavier.JPG",
        "tags": "",
        "email": "xavier.chantry@intersec.com",
        "id": "xavier.chantry@intersec.com",
        "parentId": "rawad.zgheib@intersec.com"
    },
    {
        "firstname": "Yacine",
        "lastname": "Boudiaf",
        "position": "Developer",
        "n+1": "alexis.brasy@intersec.com",
        "img": "intersecAmazingPeople/Yacine Boudiaf/Boudiaf.Yacine.jpg",
        "tags": "",
        "email": "yacine.boudiaf@intersec.com",
        "id": "yacine.boudiaf@intersec.com",
        "parentId": "alexis.brasy@intersec.com"
    },
    {
        "firstname": "Yann",
        "lastname": "Chevalier",
        "position": "CEO",
        "n+1": "",
        "img": "intersecAmazingPeople/Yann Chevalier/CHEVALIER.Yann.jpg",
        "tags": "management",
        "email": "yann.chevalier@intersec.com",
        "id": "yann.chevalier@intersec.com",
        "parentId": ""
    },
    {
        "firstname": "Yann",
        "lastname": "Kagan",
        "position": "Software Architect",
        "n+1": "rawad.zgheib@intersec.com",
        "img": "intersecAmazingPeople/Yann Kagan/Kagan.Yann.jpg",
        "tags": "",
        "email": "yann.kagan@intersec.com",
        "id": "yann.kagan@intersec.com",
        "parentId": "rawad.zgheib@intersec.com"
    },
    {
        "firstname": "Yannick",
        "lastname": "Li",
        "position": "C Developer",
        "n+1": "nassim.mnafeg@intersec.com",
        "img": "intersecAmazingPeople/Yannick Li/Li.Yannick.jpg",
        "tags": "",
        "email": "yannick.li@intersec.com",
        "id": "yannick.li@intersec.com",
        "parentId": "nassim.mnafeg@intersec.com"
    },
    {
        "firstname": "Yassin",
        "lastname": "Sekri",
        "position": "Integration Engineer",
        "n+1": "mohit.maheshwari@intersec.com",
        "img": "",
        "tags": "",
        "email": "yassin.sekri@intersec.com",
        "id": "yassin.sekri@intersec.com",
        "parentId": "mohit.maheshwari@intersec.com"
    },
    {
        "firstname": "Yohann",
        "lastname": "Balawender",
        "position": "Product Owner",
        "n+1": "kamal.fadlaoui@intersec.com",
        "img": "intersecAmazingPeople/Yohann Balawender/Balawander.Yohann.jpg",
        "tags": "",
        "email": "yohann.balawender@intersec.com",
        "id": "yohann.balawender@intersec.com",
        "parentId": "kamal.fadlaoui@intersec.com"
    },
    {
        "firstname": "Yonghaw",
        "lastname": "Goh",
        "position": "Pre Sales",
        "n+1": "ingolf.ruh@intersec.com",
        "img": "intersecAmazingPeople/Yonghaw Goh/Yonghaw_GOH.jpg",
        "tags": "",
        "email": "yonghaw.goh@intersec.com",
        "id": "yonghaw.goh@intersec.com",
        "parentId": "ingolf.ruh@intersec.com"
    },
    {
        "firstname": "Yossef",
        "lastname": "Rostaqi",
        "position": "C Developer",
        "n+1": "rawad.zgheib@intersec.com",
        "img": "intersecAmazingPeople/Yossef Rostaqi/Rostaqi.Yossef.jpg",
        "tags": "",
        "email": "yossef.rostaqi@intersec.com",
        "id": "yossef.rostaqi@intersec.com",
        "parentId": "rawad.zgheib@intersec.com"
    },
    {
        "firstname": "Oyo",
        "lastname": "Ndoro",
        "position": "VP Talent",
        "n+1": "yann.chevalier@intersec.com",
        "img": "intersecAmazingPeople/Oyo Ndoro/NDORO.Oyo.jpg",
        "tags": "management",
        "email": "oyo.ndoro@intersec.com",
        "id": "oyo.ndoro@intersec.com",
        "parentId": "yann.chevalier@intersec.com"
    },
    {
        "firstname": "Abdelmoula",
        "lastname": "Ousfour",
        "position": "Solution Architect",
        "n+1": "nicolas.najman@intersec.com",
        "img": "intersecAmazingPeople/Abdelmoula El Ousfour/Abdelmoula.Elousfour.jpg",
        "tags": "",
        "email": "abdelmoula.ousfour@intersec.com",
        "id": "abdelmoula.ousfour@intersec.com",
        "parentId": "nicolas.najman@intersec.com"
    }
]